rclone_manager/__init__.py
rclone_manager/rclone.py
rclone_manager/task.py
rclone_manager-0.0.2.dist-info/LICENSE
rclone_manager-0.0.2.dist-info/METADATA
rclone_manager-0.0.2.dist-info/WHEEL
rclone_manager-0.0.2.dist-info/top_level.txt
rclone_manager-0.0.2.dist-info/RECORD
