Metadata-Version: 2.1
Name: rclone-manager
Version: 0.0.2
Summary: Define multiple tasks using rclone
Home-page: https://github.com/batuhan0sanli/rclone-manager
Author: batuhan0sanli
Author-email: batuhansanli@gmail.com
License: MIT
Keywords: rclone manager sync copy move file
Platform: UNKNOWN
Classifier: Development Status :: 3 - Alpha
Classifier: Intended Audience :: Developers
Classifier: Topic :: Software Development :: Build Tools
Classifier: License :: OSI Approved :: MIT License
Classifier: Programming Language :: Python :: 3
Requires-Python: >=3.8
License-File: LICENSE
